pyinheritance/__init__.py
pyinheritance/class_node.py
pyinheritance/example.py
pyinheritance-0.1.dist-info/LICENSE
pyinheritance-0.1.dist-info/METADATA
pyinheritance-0.1.dist-info/WHEEL
pyinheritance-0.1.dist-info/top_level.txt
pyinheritance-0.1.dist-info/RECORD
