Metadata-Version: 2.1
Name: pyinheritance
Version: 0.1
Summary: A Python tool to model inheritance hierarchy of Python class
Home-page: https://github.com/whatsBehind/pyinheritance
Author: puyanh
Author-email: whatsbehind1@gmail.com
License: MIT
Classifier: Programming Language :: Python :: 3
Classifier: License :: OSI Approved :: MIT License
Classifier: Operating System :: OS Independent
Requires-Python: >=3.10
License-File: LICENSE
Requires-Dist: pytest
Requires-Dist: graphviz
Provides-Extra: testing
Requires-Dist: pytest ; extra == 'testing'
